<?xml version="1.0" encoding="utf-8"?>
<dropmanager>
	<path>drop/2000.xml</path>
	<path>drop/2001.xml</path>
	<path>drop/2002.xml</path>
	<path>drop/2003.xml</path>
	<path>drop/2004.xml</path>
	<path>drop/2005.xml</path>
	<path>drop/2006.xml</path>
	<path>drop/2007.xml</path>
	<path>drop/2008.xml</path>
	<path>drop/2009.xml</path>
	<path>drop/2010.xml</path>
	<path>drop/2011.xml</path>
	<path>drop/2012.xml</path>
	<path>drop/2013.xml</path>
	<path>drop/2014.xml</path>
	<path>drop/2015.xml</path>
	<path>drop/2016.xml</path>
	<path>drop/2017.xml</path>
	<path>drop/2018.xml</path>
	<path>drop/2019.xml</path>
	<path>drop/2020.xml</path>
	<path>drop/2021.xml</path>
	<path>drop/2022.xml</path>
	<path>drop/2023.xml</path>
	<path>drop/2024.xml</path>
	<path>drop/2025.xml</path>
	<path>drop/2026.xml</path>
	<path>drop/2027.xml</path>
	<path>drop/2028.xml</path>
	<path>drop/2029.xml</path>
	<path>drop/2030.xml</path>
	<path>drop/2031.xml</path>
	<path>drop/2032.xml</path>
	<path>drop/2033.xml</path>
	<path>drop/2034.xml</path>
	<path>drop/2035.xml</path>
	<path>drop/2036.xml</path>
	<path>drop/2037.xml</path>
	<path>drop/2038.xml</path>
	<path>drop/2039.xml</path>
	<path>drop/2040.xml</path>
	<path>drop/2041.xml</path>
	<path>drop/2042.xml</path>
	<path>drop/2043.xml</path>
	<path>drop/2044.xml</path>
	<path>drop/2045.xml</path>
	<path>drop/2046.xml</path>
	<path>drop/2047.xml</path>
	<path>drop/2048.xml</path>
	<path>drop/2049.xml</path>
	<path>drop/2050.xml</path>
	<path>drop/2051.xml</path>
	<path>drop/2052.xml</path>
	<path>drop/2053.xml</path>
	<path>drop/2054.xml</path>
	<path>drop/2055.xml</path>
	<path>drop/2056.xml</path>
	<path>drop/2057.xml</path>
	<path>drop/2058.xml</path>
	<path>drop/2059.xml</path>
	<path>drop/2060.xml</path>
	<path>drop/2061.xml</path>
	<path>drop/2062.xml</path>
	<path>drop/2063.xml</path>
	<path>drop/2064.xml</path>
	<path>drop/2065.xml</path>
	<path>drop/2066.xml</path>
	<path>drop/2067.xml</path>
	<path>drop/2068.xml</path>
	<path>drop/2069.xml</path>
	<path>drop/2070.xml</path>
	<path>drop/2071.xml</path>
	<path>drop/2072.xml</path>
	<path>drop/2073.xml</path>
	<path>drop/2074.xml</path>
	<path>drop/2075.xml</path>
	<path>drop/2076.xml</path>
	<path>drop/2077.xml</path>
	<path>drop/2078.xml</path>
	<path>drop/2079.xml</path>
	<path>drop/2080.xml</path>
	<path>drop/2081.xml</path>
	<path>drop/2082.xml</path>
	<path>drop/2083.xml</path>
	<path>drop/2084.xml</path>
	<path>drop/2085.xml</path>
	<path>drop/2086.xml</path>
	<path>drop/2087.xml</path>
	<path>drop/2088.xml</path>
	<path>drop/2089.xml</path>
	<path>drop/2090.xml</path>
	<path>drop/2091.xml</path>
	<path>drop/2092.xml</path>
	<path>drop/2093.xml</path>
	<path>drop/2094.xml</path>
	<path>drop/2095.xml</path>
	<path>drop/2096.xml</path>
	<path>drop/2097.xml</path>
	<path>drop/2098.xml</path>
	<path>drop/2099.xml</path>
	<path>drop/2100.xml</path>
	<path>drop/2101.xml</path>
	<path>drop/2102.xml</path>
	<path>drop/2103.xml</path>
	<path>drop/2104.xml</path>
	<path>drop/2105.xml</path>
	<path>drop/2106.xml</path>
	<path>drop/2107.xml</path>
	<path>drop/2108.xml</path>
	<path>drop/2109.xml</path>
	<path>drop/2110.xml</path>
	<path>drop/2111.xml</path>
	<path>drop/2300.xml</path>
	<path>drop/2301.xml</path>
	<path>drop/2302.xml</path>
	<path>drop/2303.xml</path>
	<path>drop/2304.xml</path>
	<path>drop/2305.xml</path>
	<path>drop/2306.xml</path>
	<path>drop/2307.xml</path>
	<path>drop/2308.xml</path>
	<path>drop/2309.xml</path>
	<path>drop/2310.xml</path>
	<path>drop/2112.xml</path>
	<path>drop/2113.xml</path>
	<path>drop/2114.xml</path>
	<path>drop/2115.xml</path>
	<path>drop/2116.xml</path>
	<path>drop/2117.xml</path>
	<path>drop/2118.xml</path>
	<path>drop/2119.xml</path>
	<path>drop/2120.xml</path>
	<path>drop/2121.xml</path>
	<path>drop/2122.xml</path>
	<path>drop/2123.xml</path>
	<path>drop/2124.xml</path>
	<path>drop/2125.xml</path>
	<path>drop/2126.xml</path>
	<path>drop/2127.xml</path>
	<path>drop/2128.xml</path>
	<path>drop/2129.xml</path>
	<path>drop/2130.xml</path>
	<path>drop/2131.xml</path>
	<path>drop/2132.xml</path>
	<path>drop/2133.xml</path>
	<path>drop/2134.xml</path>
	<path>drop/2135.xml</path>
	<path>drop/2136.xml</path>
	<path>drop/2137.xml</path>
	<path>drop/2138.xml</path>
	<path>drop/2139.xml</path>
	<path>drop/2140.xml</path>
	<path>drop/2141.xml</path>
	<path>drop/2142.xml</path>
	<path>drop/2143.xml</path>
	<path>drop/2144.xml</path>
	<path>drop/2145.xml</path>
	<path>drop/2146.xml</path>
	<path>drop/2147.xml</path>
	<path>drop/2148.xml</path>
	<path>drop/2149.xml</path>
	<path>drop/2150.xml</path>
	<path>drop/2151.xml</path>
	<path>drop/2152.xml</path>
	<path>drop/2153.xml</path>
	<path>drop/2154.xml</path>
	<path>drop/2155.xml</path>
	<path>drop/2156.xml</path>
	<path>drop/2157.xml</path>
	<path>drop/2158.xml</path>
	<path>drop/2159.xml</path>
	<path>drop/2160.xml</path>
	<path>drop/2161.xml</path>
	<path>drop/2162.xml</path>
	<path>drop/2163.xml</path>
	<path>drop/2164.xml</path>
	<path>drop/2165.xml</path>
	<path>drop/2166.xml</path>
	<path>drop/2167.xml</path>
	<path>drop/2168.xml</path>
	<path>drop/2169.xml</path>
	<path>drop/2170.xml</path>
	<path>drop/2171.xml</path>
	<path>drop/2172.xml</path>
	<path>drop/2176.xml</path>
	<path>drop/2177.xml</path>
	<path>drop/2178.xml</path>
	<path>drop/2179.xml</path>
	<path>drop/2180.xml</path>
	<path>drop/2181.xml</path>
	<path>drop/2182.xml</path>
	<path>drop/2183.xml</path>
	<path>drop/2184.xml</path>
	<path>drop/2185.xml</path>
	<path>drop/2186.xml</path>
	<path>drop/2187.xml</path>
	<path>drop/2188.xml</path>
	<path>drop/2189.xml</path>
	<path>drop/2190.xml</path>
	<path>drop/2191.xml</path>
	<path>drop/2192.xml</path>
	<path>drop/2193.xml</path>
	<path>drop/2194.xml</path>
	<path>drop/2195.xml</path>
	<path>drop/2196.xml</path>
	<path>drop/2197.xml</path>
	<path>drop/2200.xml</path>
	<path>drop/3001.xml</path>
	<path>drop/3002.xml</path>
	<path>drop/3003.xml</path>
	<path>drop/3101.xml</path>
	<path>drop/3102.xml</path>
	<path>drop/3103.xml</path>
	<path>drop/3104.xml</path>
	<path>drop/3105.xml</path>
	<path>drop/3106.xml</path>
	<path>drop/3107.xml</path>
	<path>drop/3108.xml</path>
	<path>drop/3109.xml</path>
	<path>drop/3110.xml</path>
	<path>drop/3111.xml</path>
	<path>drop/3112.xml</path>
	<path>drop/3113.xml</path>
	<path>drop/3114.xml</path>
	<path>drop/3115.xml</path>
	<path>drop/3116.xml</path>
	<path>drop/3117.xml</path>
	<path>drop/3118.xml</path>
	<path>drop/3119.xml</path>
	<path>drop/3120.xml</path>
	<path>drop/3205.xml</path>
	<path>drop/3206.xml</path>
	<path>drop/3207.xml</path>
	<path>drop/3208.xml</path>
	<path>drop/3210.xml</path>
	<path>drop/3212.xml</path>
	<path>drop/3214.xml</path>
	<path>drop/3216.xml</path>
	<path>drop/3218.xml</path>
	<path>drop/3220.xml</path>
	<path>drop/3221.xml</path>
	<path>drop/2201.xml</path>
	<path>drop/2202.xml</path>
	<path>drop/2203.xml</path>
	<path>drop/2204.xml</path>
	<path>drop/2205.xml</path>
	<path>drop/2206.xml</path>
	<path>drop/2207.xml</path>
	<path>drop/2208.xml</path>
	<path>drop/2209.xml</path>
	<path>drop/2210.xml</path>
	<path>drop/2211.xml</path>
	<path>drop/2212.xml</path>
	<path>drop/2173.xml</path>
	<path>drop/2174.xml</path>
	<path>drop/2175.xml</path>
	<path>drop/2213.xml</path>
	<path>drop/2500.xml</path>
	<path>drop/2501.xml</path>
	<path>drop/2502.xml</path>
	<path>drop/2503.xml</path>
	<path>drop/2504.xml</path>
	<path>drop/2505.xml</path>
	<path>drop/2506.xml</path>
	<path>drop/2507.xml</path>
	<path>drop/2508.xml</path>
	<path>drop/2509.xml</path>
	<path>drop/2510.xml</path>
	<path>drop/2511.xml</path>
	<path>drop/2512.xml</path>
	<path>drop/2513.xml</path>
	<path>drop/2514.xml</path>
	<path>drop/2515.xml</path>
	<path>drop/2516.xml</path>
	<path>drop/2517.xml</path>
	<path>drop/2518.xml</path>
	<path>drop/2519.xml</path>
	<path>drop/2520.xml</path>
	<path>drop/2521.xml</path>
	<path>drop/2522.xml</path>
	<path>drop/2523.xml</path>
	<path>drop/2524.xml</path>
	<path>drop/2525.xml</path>
	<path>drop/2526.xml</path>
	<path>drop/2527.xml</path>
	<path>drop/2528.xml</path>
	<path>drop/2529.xml</path>
	<path>drop/2530.xml</path>
	<path>drop/2531.xml</path>
	<path>drop/2532.xml</path>
	<path>drop/2533.xml</path>
	<path>drop/4001.xml</path>
	<path>drop/4002.xml</path>
	<path>drop/4003.xml</path>
	<path>drop/4004.xml</path>
	<path>drop/4005.xml</path>
	<path>drop/4006.xml</path>
	<path>drop/4007.xml</path>
	<path>drop/4008.xml</path>
	<path>drop/4009.xml</path>
	<path>drop/4010.xml</path>
	<path>drop/4011.xml</path>
	<path>drop/4012.xml</path>
	<path>drop/4013.xml</path>
	<path>drop/4014.xml</path>
	<path>drop/4015.xml</path>
	<path>drop/4016.xml</path>
	<path>drop/4017.xml</path>
	<path>drop/4018.xml</path>
	<path>drop/4019.xml</path>
	<path>drop/4020.xml</path>
	<path>drop/4021.xml</path>
	<path>drop/4022.xml</path>
	<path>drop/4023.xml</path>
	<path>drop/4024.xml</path>
	<path>drop/4025.xml</path>
	<path>drop/4026.xml</path>
	<path>drop/4027.xml</path>
	<path>drop/4028.xml</path>
	<path>drop/4029.xml</path>
	<path>drop/4030.xml</path>
	<path>drop/4031.xml</path>
	<path>drop/4032.xml</path>
	<path>drop/4033.xml</path>
	<path>drop/4034.xml</path>
	<path>drop/4035.xml</path>
	<path>drop/4036.xml</path>
	<path>drop/4037.xml</path>
	<path>drop/4038.xml</path>
	<path>drop/4039.xml</path>
	<path>drop/4040.xml</path>
	<path>drop/4041.xml</path>
	<path>drop/4042.xml</path>
	<path>drop/4043.xml</path>
	<path>drop/4044.xml</path>
	<path>drop/4045.xml</path>
	<path>drop/4046.xml</path>
	<path>drop/4047.xml</path>
	<path>drop/4048.xml</path>
	<path>drop/4049.xml</path>
	<path>drop/4050.xml</path>
	<path>drop/4051.xml</path>
	<path>drop/4052.xml</path>
	<path>drop/4053.xml</path>
	<path>drop/4054.xml</path>
	<path>drop/4055.xml</path>
	<path>drop/4056.xml</path>
	<path>drop/4057.xml</path>
	<path>drop/4058.xml</path>
	<path>drop/4059.xml</path>
	<path>drop/4060.xml</path>
	<path>drop/4061.xml</path>
	<path>drop/4062.xml</path>
	<path>drop/4063.xml</path>
	<path>drop/4064.xml</path>
	<path>drop/4065.xml</path>
	<path>drop/4066.xml</path>
	<path>drop/4067.xml</path>
	<path>drop/4068.xml</path>
	<path>drop/4069.xml</path>
	<path>drop/4070.xml</path>
	<path>drop/4071.xml</path>
	<path>drop/4072.xml</path>
	<path>drop/4073.xml</path>
	<path>drop/4074.xml</path>
	<path>drop/4075.xml</path>
	<path>drop/4076.xml</path>
	<path>drop/4077.xml</path>
	<path>drop/4078.xml</path>
	<path>drop/4079.xml</path>
	<path>drop/4080.xml</path>
	<path>drop/4081.xml</path>
	<path>drop/4082.xml</path>
	<path>drop/4083.xml</path>
	<path>drop/4084.xml</path>
	<path>drop/4085.xml</path>
	<path>drop/4086.xml</path>
	<path>drop/4087.xml</path>
	<path>drop/4088.xml</path>
	<path>drop/4089.xml</path>
	<path>drop/4090.xml</path>
	<path>drop/4091.xml</path>
	<path>drop/4092.xml</path>
	<path>drop/4093.xml</path>
	<path>drop/4094.xml</path>
	<path>drop/4095.xml</path>
	<path>drop/4096.xml</path>
	<path>drop/4097.xml</path>
	<path>drop/4098.xml</path>
	<path>drop/4099.xml</path>
	<path>drop/4100.xml</path>
	<path>drop/4101.xml</path>
	<path>drop/4102.xml</path>
	<path>drop/4103.xml</path>
	<path>drop/4104.xml</path>
	<path>drop/4105.xml</path>
	<path>drop/4106.xml</path>
	<path>drop/4107.xml</path>
	<path>drop/4108.xml</path>
	<path>drop/4109.xml</path>
	<path>drop/4110.xml</path>
	<path>drop/4111.xml</path>
	<path>drop/4112.xml</path>
	<path>drop/4113.xml</path>
	<path>drop/4114.xml</path>
	<path>drop/4115.xml</path>
	<path>drop/4116.xml</path>
	<path>drop/4117.xml</path>
	<path>drop/4118.xml</path>
	<path>drop/4119.xml</path>
	<path>drop/4120.xml</path>
	<path>drop/4121.xml</path>
	<path>drop/4122.xml</path>
	<path>drop/4123.xml</path>
	<path>drop/4124.xml</path>
	<path>drop/4125.xml</path>
	<path>drop/4126.xml</path>
	<path>drop/4127.xml</path>
	<path>drop/4128.xml</path>
	<path>drop/4129.xml</path>
	<path>drop/4130.xml</path>
	<path>drop/4131.xml</path>
	<path>drop/4132.xml</path>
	<path>drop/4133.xml</path>
	<path>drop/4134.xml</path>
	<path>drop/4135.xml</path>
	<path>drop/4136.xml</path>
	<path>drop/4137.xml</path>
	<path>drop/4138.xml</path>
	<path>drop/4139.xml</path>
	<path>drop/4140.xml</path>
	<path>drop/4141.xml</path>
	<path>drop/4142.xml</path>
	<path>drop/4143.xml</path>
	<path>drop/4144.xml</path>
	<path>drop/4145.xml</path>
	<path>drop/4146.xml</path>
	<path>drop/4147.xml</path>
	<path>drop/4148.xml</path>
	<path>drop/4149.xml</path>
	<path>drop/4150.xml</path>
	<path>drop/4151.xml</path>
	<path>drop/4152.xml</path>
	<path>drop/4153.xml</path>
	<path>drop/4154.xml</path>
	<path>drop/4155.xml</path>
	<path>drop/4156.xml</path>
	<path>drop/4157.xml</path>
	<path>drop/4158.xml</path>
	<path>drop/4159.xml</path>
	<path>drop/4160.xml</path>
	<path>drop/4161.xml</path>
	<path>drop/4162.xml</path>
	<path>drop/4163.xml</path>
	<path>drop/4164.xml</path>
	<path>drop/4165.xml</path>
	<path>drop/4166.xml</path>
	<path>drop/4167.xml</path>
	<path>drop/4168.xml</path>
	<path>drop/4169.xml</path>
	<path>drop/4170.xml</path>
	<path>drop/4171.xml</path>
	<path>drop/4172.xml</path>
	<path>drop/4173.xml</path>
	<path>drop/4174.xml</path>
	<path>drop/4175.xml</path>
	<path>drop/4176.xml</path>
	<path>drop/4177.xml</path>
	<path>drop/4178.xml</path>
	<path>drop/4179.xml</path>
	<path>drop/4180.xml</path>
	<path>drop/4181.xml</path>
	<path>drop/4182.xml</path>
	<path>drop/4183.xml</path>
	<path>drop/4184.xml</path>
	<path>drop/4185.xml</path>
	<path>drop/4186.xml</path>
	<path>drop/4187.xml</path>
	<path>drop/4188.xml</path>
	<path>drop/4189.xml</path>
	<path>drop/4190.xml</path>
	<path>drop/4191.xml</path>
	<path>drop/4192.xml</path>
	<path>drop/4193.xml</path>
	<path>drop/4194.xml</path>
	<path>drop/4195.xml</path>
	<path>drop/4196.xml</path>
	<path>drop/4197.xml</path>
	<path>drop/4198.xml</path>
	<path>drop/4199.xml</path>
	<path>drop/4200.xml</path>
	<path>drop/4201.xml</path>
	<path>drop/4202.xml</path>
	<path>drop/4203.xml</path>
	<path>drop/4204.xml</path>
	<path>drop/4205.xml</path>
	<path>drop/4206.xml</path>
	<path>drop/4207.xml</path>
	<path>drop/4208.xml</path>
	<path>drop/4209.xml</path>
	<path>drop/4210.xml</path>
	<path>drop/4211.xml</path>
	<path>drop/4212.xml</path>
	<path>drop/4213.xml</path>
	<path>drop/2214.xml</path>
	<path>drop/4214.xml</path>
	<path>drop/4215.xml</path>
	<path>drop/4216.xml</path>
	<path>drop/4217.xml</path>
	<path>drop/4218.xml</path>
	<path>drop/4219.xml</path>
	<path>drop/4220.xml</path>
	<path>drop/4221.xml</path>
	<path>drop/4222.xml</path>
	<path>drop/4223.xml</path>
	<path>drop/4224.xml</path>
	<path>drop/4225.xml</path>
	<path>drop/4226.xml</path>
	<path>drop/4227.xml</path>
	<path>drop/4228.xml</path>
	<path>drop/4229.xml</path>
	<path>drop/4230.xml</path>
	<path>drop/4231.xml</path>
	<path>drop/4232.xml</path>
	<path>drop/4233.xml</path>
	<path>drop/4234.xml</path>
	<path>drop/4235.xml</path>
	<path>drop/4236.xml</path>
	<path>drop/4237.xml</path>
	<path>drop/4238.xml</path>
	<path>drop/4239.xml</path>
	<path>drop/4240.xml</path>
	<path>drop/4241.xml</path>
	<path>drop/4242.xml</path>
	<path>drop/4243.xml</path>
	<path>drop/4244.xml</path>
	<path>drop/4245.xml</path>
	<path>drop/4246.xml</path>
	<path>drop/4247.xml</path>
	<path>drop/4248.xml</path>
	<path>drop/4249.xml</path>
	<path>drop/4250.xml</path>
	<path>drop/4251.xml</path>
	<path>drop/4252.xml</path>
	<path>drop/4253.xml</path>
	<path>drop/4254.xml</path>
	<path>drop/4255.xml</path>
	<path>drop/4256.xml</path>
	<path>drop/4257.xml</path>
	<path>drop/4258.xml</path>
	<path>drop/4259.xml</path>
	<path>drop/4260.xml</path>
	<path>drop/4261.xml</path>
	<path>drop/4262.xml</path>
	<path>drop/4263.xml</path>
	<path>drop/4264.xml</path>
	<path>drop/4265.xml</path>
	<path>drop/4266.xml</path>
	<path>drop/4267.xml</path>
	<path>drop/4268.xml</path>
	<path>drop/4269.xml</path>
	<path>drop/4270.xml</path>
	<path>drop/4271.xml</path>
	<path>drop/4272.xml</path>
	<path>drop/4273.xml</path>
	<path>drop/4274.xml</path>
	<path>drop/4275.xml</path>
	<path>drop/4276.xml</path>
	<path>drop/4277.xml</path>
	<path>drop/4278.xml</path>
	<path>drop/4279.xml</path>
	<path>drop/4280.xml</path>
	<path>drop/4281.xml</path>
	<path>drop/4282.xml</path>
	<path>drop/4283.xml</path>
	<path>drop/4284.xml</path>
	<path>drop/4285.xml</path>
	<path>drop/4286.xml</path>
	<path>drop/4287.xml</path>
	<path>drop/4288.xml</path>
	<path>drop/4289.xml</path>
	<path>drop/4290.xml</path>
	<path>drop/4291.xml</path>
	<path>drop/4292.xml</path>
	<path>drop/4293.xml</path>
	<path>drop/4294.xml</path>
	<path>drop/4295.xml</path>
	<path>drop/4296.xml</path>
	<path>drop/4297.xml</path>
	<path>drop/4298.xml</path>
	<path>drop/4299.xml</path>
	<path>drop/4300.xml</path>
	<path>drop/4301.xml</path>
	<path>drop/4302.xml</path>
	<path>drop/4303.xml</path>
	<path>drop/4304.xml</path>
	<path>drop/4305.xml</path>
	<path>drop/4306.xml</path>
	<path>drop/4307.xml</path>
	<path>drop/4308.xml</path>
	<path>drop/4309.xml</path>
	<path>drop/4310.xml</path>
	<path>drop/4311.xml</path>
	<path>drop/4312.xml</path>
	<path>drop/4313.xml</path>
	<path>drop/4314.xml</path>
	<path>drop/4315.xml</path>
	<path>drop/4316.xml</path>
	<path>drop/4317.xml</path>
	<path>drop/4318.xml</path>
	<path>drop/4319.xml</path>
	<path>drop/4320.xml</path>
	<path>drop/4321.xml</path>
	<path>drop/4322.xml</path>
	<path>drop/4323.xml</path>
	<path>drop/4324.xml</path>
	<path>drop/4325.xml</path>
	<path>drop/4326.xml</path>
	<path>drop/4327.xml</path>
	<path>drop/4328.xml</path>
	<path>drop/4329.xml</path>
	<path>drop/4330.xml</path>
	<path>drop/4331.xml</path>
	<path>drop/4332.xml</path>
	<path>drop/4333.xml</path>
	<path>drop/4334.xml</path>
	<path>drop/4335.xml</path>
	<path>drop/4336.xml</path>
	<path>drop/4337.xml</path>
	<path>drop/4338.xml</path>
	<path>drop/4339.xml</path>
	<path>drop/4340.xml</path>
	<path>drop/4341.xml</path>
	<path>drop/4342.xml</path>
	<path>drop/4343.xml</path>
	<path>drop/4344.xml</path>
	<path>drop/4345.xml</path>
	<path>drop/4346.xml</path>
	<path>drop/4347.xml</path>
	<path>drop/4348.xml</path>
	<path>drop/4349.xml</path>
	<path>drop/4350.xml</path>
	<path>drop/4351.xml</path>
	<path>drop/4352.xml</path>
	<path>drop/4353.xml</path>
	<path>drop/4354.xml</path>
	<path>drop/4355.xml</path>
	<path>drop/4356.xml</path>
	<path>drop/4357.xml</path>
	<path>drop/4358.xml</path>
	<path>drop/4359.xml</path>
	<path>drop/4360.xml</path>
	<path>drop/4361.xml</path>
	<path>drop/4362.xml</path>
	<path>drop/4363.xml</path>
	<path>drop/4364.xml</path>
	<path>drop/4365.xml</path>
	<path>drop/4366.xml</path>
	<path>drop/4367.xml</path>
	<path>drop/4368.xml</path>
	<path>drop/4369.xml</path>
	<path>drop/4370.xml</path>
	<path>drop/4371.xml</path>
	<path>drop/4372.xml</path>
	<path>drop/4373.xml</path>
	<path>drop/4374.xml</path>
	<path>drop/4375.xml</path>
	<path>drop/4376.xml</path>
	<path>drop/4377.xml</path>
	<path>drop/4378.xml</path>
	<path>drop/4379.xml</path>
	<path>drop/4380.xml</path>
	<path>drop/4381.xml</path>
	<path>drop/4382.xml</path>
	<path>drop/4383.xml</path>
	<path>drop/4384.xml</path>
	<path>drop/4385.xml</path>
	<path>drop/4386.xml</path>
	<path>drop/4387.xml</path>
	<path>drop/4388.xml</path>
	<path>drop/4389.xml</path>
	<path>drop/4390.xml</path>
	<path>drop/4391.xml</path>
	<path>drop/4392.xml</path>
	<path>drop/4393.xml</path>
	<path>drop/4394.xml</path>
	<path>drop/4395.xml</path>
	<path>drop/4396.xml</path>
	<path>drop/4397.xml</path>
	<path>drop/4398.xml</path>
	<path>drop/4399.xml</path>
	<path>drop/4400.xml</path>
	<path>drop/4401.xml</path>
	<path>drop/4402.xml</path>
	<path>drop/4403.xml</path>
	<path>drop/4404.xml</path>
	<path>drop/4405.xml</path>
	<path>drop/4406.xml</path>
	<path>drop/4407.xml</path>
	<path>drop/4408.xml</path>
	<path>drop/4409.xml</path>
	<path>drop/4410.xml</path>
	<path>drop/4411.xml</path>
	<path>drop/4412.xml</path>
	<path>drop/4413.xml</path>
	<path>drop/4414.xml</path>
	<path>drop/4415.xml</path>
	<path>drop/4416.xml</path>
	<path>drop/4417.xml</path>
	<path>drop/4418.xml</path>
	<path>drop/4419.xml</path>
	<path>drop/4420.xml</path>
	<path>drop/4421.xml</path>
	<path>drop/4422.xml</path>
</dropmanager>
